{"followLerp":0.04,"defaultCamZoom":1,"sprites":[{"pos":[-325,-218],"src":"street_bgweek4","shader":"","beatTween":{"x":0,"y":0,"ease":"linear"},"alpha":1,"scrollFactor":[1,1],"antialiasing":true,"name":"street_bgweek4","animation":null,"type":"Bitmap","scale":2.9},{"pos":[427,6],"src":"","shader":"","beatTween":{"x":0,"y":0,"ease":"linear"},"alpha":1,"scrollFactor":[0.95,0.95],"antialiasing":true,"name":"Girlfriend","animation":null,"type":"GF","scale":1},{"pos":[48,317],"src":"","shader":"","beatTween":{"x":0,"y":0,"ease":"linear"},"alpha":1,"scrollFactor":[1,1],"antialiasing":true,"name":"Dad","animation":null,"type":"Dad","scale":1},{"pos":[1032,-1],"src":"","shader":"","beatTween":{"x":0,"y":0,"ease":"linear"},"alpha":1,"scrollFactor":[1,1],"antialiasing":true,"name":"Boyfriend","animation":null,"type":"BF","scale":1}],"gfOffset":[27,-124],"dadOffset":[-52,217],"bfOffset":[262,-101]}